pytekukko/__init__.py
pytekukko/exceptions.py
pytekukko/models.py
pytekukko/py.typed
pytekukko/examples/__init__.py
pytekukko/examples/print_collection_schedules.py
pytekukko/examples/print_invoice_headers.py
pytekukko/examples/print_next_collections.py
pytekukko-0.17.0.dist-info/licenses/LICENSE
pytekukko-0.17.0.dist-info/METADATA
pytekukko-0.17.0.dist-info/WHEEL
pytekukko-0.17.0.dist-info/entry_points.txt
pytekukko-0.17.0.dist-info/top_level.txt
pytekukko-0.17.0.dist-info/RECORD
