Metadata-Version: 2.4
Name: pytekukko
Version: 0.17.0
Summary: Jätekukko Omakukko API client
Author-email: Ville Skyttä <ville.skytta@iki.fi>
License: 
Project-URL: Homepage, https://github.com/scop/pytekukko
Project-URL: Changelog, https://github.com/scop/pytekukko/blob/main/CHANGELOG.md
Classifier: Development Status :: 4 - Beta
Classifier: Framework :: AsyncIO
Classifier: Intended Audience :: Developers
Classifier: Intended Audience :: End Users/Desktop
Classifier: License :: OSI Approved :: Apache Software License
Classifier: Operating System :: OS Independent
Classifier: Programming Language :: Python :: 3 :: Only
Classifier: Typing :: Typed
Requires-Python: >=3.10
License-File: LICENSE
Requires-Dist: aiohttp~=3.4
Provides-Extra: examples
Requires-Dist: python-dotenv<2,>=0.10; extra == "examples"
Requires-Dist: icalendar<7,>=5; extra == "examples"
Dynamic: license-file
